MoreAPI/Auth.py
MoreAPI/Bilibili.py
MoreAPI/Billboard.py
MoreAPI/DouYin.py
MoreAPI/KuaiShou.py
MoreAPI/Lemon8.py
MoreAPI/TikTok.py
MoreAPI/WeiBo.py
MoreAPI/XHS.py
MoreAPI/YouTube.py
MoreAPI/__init__.py
MoreApi-0.5.3.dist-info/LICENSE
MoreApi-0.5.3.dist-info/METADATA
MoreApi-0.5.3.dist-info/WHEEL
MoreApi-0.5.3.dist-info/top_level.txt
MoreApi-0.5.3.dist-info/RECORD
