Metadata-Version: 2.1
Name: MoreApi
Version: 0.5.3
Summary: MoreAPI抖音/快手/小红书/哔哩哔哩/YouTube/微博等各视频平台非官方的RESTful API平台
Home-page: https://github.com/liulu1550/MoreAPI.git
Author: MoreCoding
Author-email: wouldmissyou@163.com
Requires-Python: >=3.7
License-File: LICENSE
Requires-Dist: requests
